describerr/__init__.py
describerr/describerr.py
describerr-0.4.0.dist-info/METADATA
describerr-0.4.0.dist-info/WHEEL
describerr-0.4.0.dist-info/entry_points.txt
describerr-0.4.0.dist-info/RECORD
