Metadata-Version: 2.1
Name: describerr
Version: 0.4.0
Summary: Simple Opinionated git log to a changelog
License: MIT
Author: Krzysztof Czeronko
Author-email: krzysztof.czeronko@gmail.com
Requires-Python: >=3.8.1,<4.0
Classifier: License :: OSI Approved :: MIT License
Classifier: Programming Language :: Python :: 3
Classifier: Programming Language :: Python :: 3.9
Classifier: Programming Language :: Python :: 3.10
Classifier: Programming Language :: Python :: 3.11
Classifier: Programming Language :: Python :: 3.12
Requires-Dist: loguru (>=0.7.0,<0.8.0)
